{
  "logistic_regression":{
    "threshold":0.5,
    "precision":0.604,
    "recall":0.758,
    "f1":0.672,
    "roc_auc":0.839,
    "pr_auc":0.746,
    "confusion_matrix":[
      [
        824,
        310
      ],
      [
        151,
        472
      ]
    ]
  },
  "random_forest":{
    "threshold":0.4,
    "precision":0.594,
    "recall":0.764,
    "f1":0.669,
    "roc_auc":0.821,
    "pr_auc":0.715,
    "confusion_matrix":[
      [
        809,
        325
      ],
      [
        147,
        476
      ]
    ]
  }
}